{
  "ru": {
    "providers": {
      "pg-soft": [
        "Leprechaun Riches",
        "Spirited Wonders",
        "Wild Bounty Showdown",
        "Fortune Tiger",
        "Mermaid Riches",
        "Fortune Ox",
        "Hawaiian Tiki",
        "Bakery Bonanza",
        "Wild Ape #3258",
        "Fortune Rabbit",
        "Safari Wilds",
        "Mask Carnival",
        "Mafia Mayhem",
        "Gemstones Gold",
        "Rave Party Fever",
        "Lucky Clover Lady",
        "Forge of Wealth"
      ],
      "PlaynGO": [
        "Treasures of Kongar",
        "Wild Survivor",
        "Gigantoonz",
        "Legacy of Dead",
        "Rich Wilde and the Tome of Madness",
        "Idol of Fortune",
        "Leprechaun's Vault",
        "Rise of Merlin",
        "Perfect Gems",
        "Dansband Pa Turne",
        "King's Mask",
        "Cash of Command",
        "Book of Dead",
        "Cat Wilde and the Pyramids of Dead",
        "Forge of Fortunes",
        "Mount M",
        "Rocco Gallo",
        "Tales of Asgard: Loki’s Fortune",
        "Fortune Rewind",
        "DIO - Killing the Dragon",
        "Rise of Gods Reckoning",
        "Secret of Dead",
        "Beasts Of Fire",
        "Boat Bonanza Down Under"
      ],
      "spinomenal": [
        "Baba Yaga Tales",
        "Majestic Bison",
        "Majestic Claws - Wild Snow",
        "The Tricksters Treasure",
        "PIN-UP Fortune",
        "Queen Of The Forest",
        "Story Of Odin",
        "Fairytale Beauties",
        "Bavarian Riches 2",
        "PIN-UP Athenas Glory",
        "Gangsters Gold - On The Run",
        "100 Lucky PIN-UPs – Spin’O’wheel",
        "Valentine Collection 20 Lines",
        "Demi Gods V",
        "Celestial Conquest",
        "PIN-UP Book Of Demi Gods 2",
        "Book Of Savannahs Queen"
      ],
      "spribe": [
        "Mines",
        "Keno",
        "Dice",
        "MiniRoulette",
        "Goal",
        "Plinko",
        "Hotline",
        "HiLo",
        "Aviator"
      ],
      "playson": [
        "Burning Wins: classic 5 lines",
        "Thunder Coins: Hold and Win",
        "Energy Coins: Hold and Win",
        "Book of Gold: Multichance",
        "Diamond Fortunator: Hold and Win",
        "Jingle Coins: Hold and Win",
        "Luxor Gold: Hold and Win",
        "Jokers Coins: Hold and Win",
        "Buffalo Power 2: Hold and Win",
        "Burning Wins x2",
        "Sherwood Coins: Hold and Win",
        "Book del Sol: Multiplier",
        "Pirate Chest: Hold and Win",
        "Royal Coins: Hold and Win",
        "Burning Fortunator",
        "Sunny Fruits: Hold and Win",
        "100 Joker Staxx",
        "Joker Expand: 5 Lines",
        "Wolf Power: Hold and Win",
        "Fruits & Jokers: 20 lines",
        "Solar King",
        "Book of Gold: Classic",
        "Divine Dragon: Hold and Win",
        "Hot Burning Wins",
        "Book of Gold: Double Chance",
        "Eagle Power: Hold and Win",
        "Rise of Egypt",
        "5 Super Sevens & Fruits",
        "5 Fortunator",
        "Sevens&Fruits: 20 Lines",
        "Solar Temple",
        "Buffalo Power Megaways",
        "Wolf Power Megaways",
        "Legend of Cleopatra",
        "3 Fruits Win: 10 Lines"
      ],
      "nolimit": [
        "Disturbed",
        "Jingle Balls",
        "Bounty Hunters",
        "Fire In The Hole xBomb",
        "Mental",
        "The Creepy Carnival",
        "Casino Win Spin",
        "Manhattan Goes Wild",
        "Coins Of Fortune",
        "Mayan Magic",
        "Hot 4 Cash",
        "Hot Nudge"
      ],
      "gamzix": [
        "Ruby Win: Hold The Spin",
        "Japanese Coin: Hold The Spin",
        "Samba Stars: Hold the Spin",
        "Sunny Coin 2: Hold The Spin",
        "Really Hot Flaming Edition",
        "Coin Win: Hold The Spin",
        "Ultra Luck",
        "3x3 Hold The Spin",
        "Pilot",
        "Burning Power",
        "PIN-UP Coin",
        "Sticky Coin: Hold the Spin",
        "Pilot Cup",
        "Pilot Coin",
        "Joker Splash",
        "Dice: Hold The Spin",
        "40 Chilli Fruits Flaming Edition",
        "40 Sweet Fruits",
        "Locky Fruits: Hold the Spin",
        "The Hottest Game", 
        "Go Wild",
        "Book Of Symbols",
        "Snow Coin: Hold The Spin",
        "GG Coin: Hold The Spin",
        "Buffalo: Ice Hold The Spin",
        "Dogs and Tails",
        "Wolf Story",
        "Dice: Hold The Spin",
        "Santa Sphere: Hold The Spin",
        "Happy Rabbit: 27 Ways",
        "Bonanza Donut Xmas",
        "Bonanza Donut",
        "Really Hot",
        "Patrick’s Coin: Hold The Spin",
        "Billie Wild",
        "Spooky Coin: Hold The Spin",
        "3X3: Hell Spin",
        "Hot Love",
        "Fruit Story: Hold the Spin",
        "Egypt Sphere: Hold the Spin",
        "Juicy Win: Hold The Spin",
        "40 Chilli Fruits",
        "Royal Chip",
        "Fruit Story",
        "Won Hundred",
        "Buffalo Coin: Hold The Spin",
        "Hot Patrick",
        "Book of Zulu",
        "Gold Mania",
        "Olympus of Luck: Hold the Spin",
        "Really Hot 2",
        "Book of Cairo",
        "Really Easter",
        "3X3: 27 Ways"
      ],
      "netgame": [
        "Royal Fruits 5: Hold n Link",
        "Frog Princess",
        "Cactus Riches: Cash Pool",
        "Pompeii Gold: Rapid Link",
        "Rich Piggies: Bonus Combo",
        "Hot Cash: Hold ‘n’ Link",
        "Wolf Reels Rapid Link",
        "Big Catch Bonanza",
        "Elephants Gold: Buy Bonus Combo",
        "Wild Buffalo: Rapid Link",
        "Wild Buffalo Hold 'N' Link",
        "Wild Buffalo Fortune Wheel",
        "Wild Buffalo",
        "Fruit Burst",
        "Golden Tree"
      ],
      "1spin4win": [
        "Book of Wild",
        "Lucky 10 Bells",
        "Coinsn Fruits Spins",
        "Mega Lucky 576",
        "Cashn Fruits Fortune 100",
        "Lucky 432 Ways",
        "Coinsn Fruits Spins",
        "PIN-UP CashnFruits 100",
        "Cash The Gold",
        "Mega Lucky 576",
        "Cashn Fruits 243",
        "Booming Fruits 243",
        "Mega Lucky 243",
        "Mega Booming Fruits",
        "Mega Lucky 100",
        "PIN-UP Fruits 243",
        "Cashn Fruits 100",
        "Allways Lucky Pot"
      ],
      "amusnet": [
        "Shining Crown",
        "Ultimate Hot",
        "Fruity Time",
        "Flaming Hot 6 Reels",
        "Kamakura",
        "Candy Palace",
        "Mighty Sparta",
        "Supreme Hot",
        "Vampire Bites",
        "Extra Crown",
        "Power Hot",
        "Phoenix Star",
        "Lucky Wood",
        "Game of Luck",
        "More Lucky & Wild",
        "Golden Coins",
        "Bulky Fruits",
        "100 Bulky Fruits",
        "Wild Goals"
      ],
        "amatic": [
        "Lucky Joker 10 Extra Gifts",
        "All Ways Hot Fruits",
        "Hot Fruits 100",
        "Lady PIN-UPs 100",
        "Lucky Joker 100",
        "Lucky Piggies 2 Hold&Win",
        "Book Of Aztec",
        "Grand Fruits",
        "Lucky Joker 40",
        "Fruit Box",
        "Joker X",
        "All Ways Hottest Fruits",
        "Hot Fruits 20 Cash Spins",
        "Lucky Joker 10",
        "Blazing Bells 20",
        "Blazing Coins 100",
        "Hot Fruits 27"
      ],
      "novomatic": [
    "Treasure Jewels",
    "5 Sevens Hold & Win",
    "Sizzling Hot",
    "Book of Ra Deluxe Buy Bonus",
    "Bananas Go Bahamas",
    "20 Mega Hotfire",
    "10 Devils Hotfire",
    "5 Super Clover",
    "Banana Splash",
    "Book Hotfire",
    "Book of Luck",
    "Ultra Hotfire",
    "Sizzling Gems",
    "Book Hotfire Buy Bonus",
    "Christmas Boom",
    "The Money Game",
    "Scarab Fortunes",
    "50 Jokers Hotfire",
    "Plenty on Twenty Hot",
    "Pharaohs Gold II",
    "Jackass Gold Hold & Win Buy Bonus",
    "Just Jewels Deluxe",
    "Faust Buy Bonus",
    "Always Hot",
    "Plenty of Fruit 40",
    "Supra Hot",
    "Royal Treasures",
    "Plenty of Fruit 20 Hot",
    "King of Cards",
    "The Magic Flute",
    "5 Sevens Hold & Win Christmas",
    "Queen of Hearts Deluxe",
    "Wings of Fire",
    "Gorilla",
    "Olivers Bar",
    "Hot Chance",
    "50 Jokers Christmas",
    "Silver Fox",
    "Flame Dancer",
    "Indian Spirit",
    "Gryphons Gold",
    "Aztec Eclipse Hold & Win",
    "Mermaids Pearl",
    "Sharky",
    "Million Dollar Heist Xtreme",
    "Book Hotfire Multichance Buy Bonus",
    "Katana",
    "River Queen",
    "Fortune God",
    "Chicago",
    "Chip Runner",
    "Riches of India",
    "5 Sevens",
    "Golden Ark",
    "Mystic Bull",
    "Magic Money",
    "The Euro Game",
    "Million Dollar Heist",
    "Book Hotfire Multichance",
    "Gold Fever",
    "5 Sevens Dice",
    "Macarena"
  ],
      "zeusplay": [
  "Great Buffalo",
  "Diamond Freeze",
  "40 Flaming Lines",
  "Nine Dragon Coins",
  "Fifteen Dragon Coins",
  "Diamonds Fortune",
  "Butterfly Hot 10",
  "Hot 27 Lines",
  "Hot Diamonds 5",
  "Hot Diamonds 20",
  "Hot Diamonds 40",
  "Royal Jewels",
  "The Divine 12th",
  "The Emperors Curse",
  "Amuns Book HD",
  "Arabian Dream Remastered",
  "Wilds and Pirates",
  "Don Mafioso",
  "The Zodiac 12 Water Edition",
  "A Fistful of Coins",
  "Disco Fever",
  "Abby And The Witch",
  "Haunted Walker",
  "Bubbles And Pearls",
  "Hot 20 Deluxe",
  "Fire 20 Deluxe",
  "Fairys Golden Path",
  "Captain Nelson Deluxe",
  "Dice Tronic",
  "Hot 5 Deluxe",
  "Dice Tronic X",
  "Extra Super Hot Bbq",
  "Farm Madness",
  "Hot Diamonds 20 Dice",
  "Dice Tronic Xl",
  "Infinium",
  "Hot Diamonds 40 Dice",
  "Lady Of The Forest",
  "Golden Dice 3",
  "Mad Cubes 25",
  "Le Mystere Du Prince",
  "Mad Cubes 50",
  "Magic Charm",
  "The Explorers Quest",
  "Page Of Fortune Deluxe",
  "Snake Eyes",
  "Star Frenzy",
  "Wild Charger",
  "The Lost Temple",
  "Super Hot Bbq",
  "Trojan Horse Tiny Heroes"
],
"bgaming": [
  "Wild Cash",
  "Lady Wolf Moon",
  "Aztec Clusters",
  "Burning Chilli X",
  "Fruit Million",
  "Lucky Lady PIN-UP",
  "Bonanza Billion",
  "Luck & Magic",
  "Lucky Ladys Clover",
  "Space XY",
  "All Lucky Clovers 100",
  "Diamond of Jungle",
  "Wild Tiger",
  "Wild West TRUEWAYS",
  "Aztec Magic Deluxe",
  "All Lucky Clovers",
  "Miss Cherry Fruits",
  "Halloween Bonanza",
  "Aviamasters",
  "Alien Fruits FS",
  "PIN-UP Bonanza",
  "Clover Bonanza",
  "Gemhalla",
  "Book Of Cats",
  "Aztec Magic Megaways",
  "Hottest 666",
  "Panda Luck",
  "Snoop Dogg Dollars",
  "Elvis Frog in Vegas",
  "Fishing Club",
  "Lucky Farm Bonanza",
  "Merge Up",
  "Gold of Minos",
  "Mechanical Clover",
  "Mummys Gold",
  "Joker Queen",
  "Slot Machine",
  "Big Atlantis Frenzy",
  "Mice & Magic Wonder Spin",
  "Book of Kemet",
  "PIN-UP Million",
  "Lucky Crew",
  "Aztec Magic Bonanza",
  "Miss Cherry Fruits Jackpot Party",
  "Lucky Dragon MultiDice X",
  "Wild Cash Dice",
  "Domnitors Treasure",
  "Gemza",
  "Road 2 Riches",
  "Voodoo People",
  "Wild Moon Thieves",
  "Gift Rush",
  "Dragon Age Hold & Win",
  "Candy Monsta",
  "Lady Wolf Moon Megaways",
  "Gold Rush with Johnny Cash",
  "All Lucky Clovers 40",
  "Beast Band",
  "Penny Pelican",
  "Potion Spells",
  "WBC Ring of Riches",
  "Grand Patron",
  "Winter Fishing Club",
  "Gangsterz",
  "Wild Cash x9990",
  "OOF The Goldmine Planet",
  "Tramp Day",
  "Wild Chicago",
  "Lucky 8 Merge Up",
  "Savage Buffalo Spirit Megaways",
  "Hit The Route",
  "Fortuna TRUEWAYS",
  "Johnny Cash",
  "Chicken Rush",
  "PIN-UP Soccermania",
  "Bone Bonanza",
  "God of Wealth Hold And Win",
  "Book of Panda Megaways",
  "Sweet Rush Megaways",
  "Wild Heart",
  "Dragons Crash",
  "Lucky Oak",
  "Capymania Green",
  "Keepers Of The Secret",
  "Krakens Hunger",
  "Catch the Gold Hold and Win",
  "Pop Zen",
  "Royal Fruits MultiLines",
  "Carnival Bonanza",
  "Forgotten",
  "Easter Heist",
  "Four Lucky Clover",
  "Maneki 88 Fortunes",
  "Aztecs Claw Wild Dice",
  "Savage Buffalo Spirit",
  "Royal High-Road",
  "Scratch Alpaca Silver",
  "Haunted Reels",
  "Hot Chilli Bells",
  "Gold Magnate",
  "Disco Party",
  "Tile Master",
  "Joker’s Million",
  "Dice Clash",
  "Golden Pride",
  "Mine Gems",
  "Catdiana",
  "Capymania Orange",
  "Monster Hunt",
  "Capymania Yellow",
  "Book Of Cats Megaways",
  "Robospin",
  "Scratch Alpaca Bronze",
  "Scratch Alpaca Gold",
  "Dice Bonanza",
  "Ice Scratch Bronze",
  "Forty Fruity Million",
  "Maneki 88 Gold",
  "Beer Bonanza",
  "Sakura Riches 60",
  "Ice Scratch Gold",
  "Elvis Frog Trueways",
  "Gift X",
  "Aztec Magic",
  "Rotating Element",
  "Lucky Ducky",
  "Ice Scratch Silver",
  "Train to Rio Grande",
  "Top Eagle",
  "Dice Million",
  "Street Power",
  "Alien Fruits 2",
  "Secret Bar Multidice X",
  "Plinko 2",
  "Aloha King Elvis",
  "Lucky Dama Muerta",
  "Dig Dig Digger",
  "Dragon’s Gold 100",
  "3 Kings Scratch",
  "Limbo XY",
  "Easter Plinko",
  "Plinko XY",
  "Minesweeper XY",
  "Rocket Dice XY",
  "Heads and Tails XY",
  "Luck & Magic Scratch",
  "Deep Sea",
  "Minesweeper",
  "Avalon: The Lost Kingdom",
  "Journey Flirt",
  "Book of Pyramids",
  "Hawaii Cocktails",
  "Jogo Do Bicho",
  "Scratch Dice",
  "All Lucky Clovers 20",
  "All Lucky Clovers 5",
  "Spin and Spell",
  "Desert Treasure",
  "Hello Easter",
  "Rocket Dice",
  "Fantasy Park",
  "Fire Lightning",
  "Lucky Blue",
  "Platinum Lightning",
  "Platinum Lightning Deluxe",
  "Princess of Sky",
  "West Town",
  "Brave Viking",
  "Cherry Fiesta",
  "Crazy Starter",
  "Domnitors",
  "French Roulette",
  "Heads and Tails",
  "Multihand Blackjack",
  "American Roulette",
  "Multihand Blackjack Pro",
  "European Roulette"
],
      "fazi": [
    "Very Hot 5",
    "Turbo Stars 40",
    "Fruits and Stars",
    "Crystal Hot 40",
    "King of Thunder",
    "Hot Stars",
    "Pyramid",
    "Christmas Presents",
    "Pirates",
    "Book of Spells Deluxe",
    "Twinkling Hot 5",
    "Retro 7 Hot",
    "Santas Presents",
    "Triple-Hot",
    "Turbo Hot 40",
    "Fruit Island Christmas",
    "Clover Coin",
    "Rainbow Sevens",
    "Crystal Hot 40 Christmas",
    "Book of Spells",
    "Fruits and Stars 40 Christmas",
    "Bonus Bells",
    "Fashion Night",
    "Mayans Battle",
    "Heating Ice Deluxe",
    "Starlight",
    "Wild Hot 40",
    "Golden Explosion",
    "Lady Triple Fortune",
    "Very Hot 5 Extreme",
    "Wild Forties Xmas",
    "Fortune Clover X2",
    "Joker Triple Double",
    "Dice Machine",
    "Book of Bruno",
    "Twinkling Hot 40",
    "Bikini Fruits",
    "Thunder Fruits",
    "20 Hot Strike",
    "Fruits and Stars Christmas",
    "Crowns and Stars",
    "Clover Royale",
    "Lollas World Christmas",
    "Hot Rush Stars Deluxe",
    "Viking Gold",
    "Hot Rush Crown Burst",
    "Turbo Hot 40 Christmas",
    "Cosmic Sevens",
    "20 Hot Strike Jackpot",
    "Special Fruits",
    "Diamond Heart x2",
    "Very Hot 40",
    "Eternal Hearts 10",
    "Golden Crown Christmas",
    "Hearts & Stars",
    "Hot Stars Christmas",
    "Jolly Presents",
    "Retro 7 Hot Christmas",
    "Lava Diamonds Christmas",
    "Bonus Epic Crown",
    "Aloha Charm",
    "Majestic Crown 10",
    "Triple Fields of Luck",
    "Wild Craps",
    "Twinkling Hot 40 Christmas",
    "Very Hot 40 Christmas",
    "Golden Crown 40",
    "Wizard",
    "Wild Hot 40 Free Spins",
    "Katanas of Time",
    "Very Hot 5 Christmas",
    "Epic Fire 40",
    "Templars Quest",
    "Pixel Hot 40",
    "Fruits and Stars 40",
    "Mystery Joker Hot",
    "Wild Hot 40 Christmas",
    "Crystals of Magic",
    "Dolphins Shine",
    "Space Guardians",
    "Book of Spells 2",
    "Turbo Hot 80",
    "Fire Clover 5",
    "Fear of Dark",
    "Wild Crown 10",
    "Jazzy Fruits",
    "Wild Paradise",
    "Money 5",
    "Fruit Island",
    "Golden Crown",
    "Havana Dice",
    "Epic Clover 40",
    "Diamond Heart 5",
    "Mayan Coins",
    "Wild Hot 40 Blow",
    "Wild 27",
    "The Crown Fruit",
    "Casino Fruits",
    "Fire Dice 5",
    "Crystal Hot 40 Free Spins",
    "Chilli Respin",
    "Wild Dice 40",
    "Mega Hot 10",
    "Postman",
    "Deep Jungle",
    "Fruity Hot 5",
    "Gold Line Dice",
    "20 Mega Flames",
    "Clovers & Stars",
    "Buffalo Dice",
    "Action Hot 20",
    "Gold Line",
    "Wild Lucky Clover",
    "10 Jingle Fruits",
    "Action Hot 40",
    "81 Vegas Crown",
    "Forest Fruits",
    "Wild Lucky Clover 2",
    "40 Dice Flames",
    "HEAT Classic 5",
    "40 Mega Flames",
    "Very Hot 40 Respin",
    "Turbo Fire",
    "Wild 81",
    "Book of Ibis",
    "Sticky Hot",
    "Lollas World",
    "Crystal Hot 40 Deluxe",
    "Crystal Jewels",
    "Winning Clover 5",
    "Star Runner",
    "Heating Fruits",
    "Dice Double",
    "Crystal Joker Hot",
    "Blow Fruits 40",
    "Turbo Stars 10",
    "Double Clover Fire",
    "Dashing Hot 5",
    "Fruity Win 20",
    "Wild Heat 40",
    "Mega Cubes Deluxe",
    "Football Victory",
    "Mega Hot 20",
    "Crystal Hot 100",
    "20 Dice Flames",
    "Summer Rush",
    "Mystic Jungle",
    "Wild Dice 10",
    "Fortune Parrot",
    "Mini Mega Cash",
    "VIP Roulette",
    "Wild Heart 5",
    "Lava Dice",
    "Epic Clover 100",
    "Spooky Spins",
    "Fluo Dice 5",
    "Fortune Clover 40",
    "Majestic Crown 20",
    "Cash Bells 40",
    "Wild Diamond 10",
    "Epic Crown 5",
    "Power of the Great",
    "Heating Ice",
    "Great Whale",
    "Da Vincis Fruits",
    "Winning Stars",
    "Island Respins",
    "Fruit Magic",
    "Fire Dice 40",
    "Monsters",
    "Lost Book",
    "Crystal Hot 80",
    "Money Standard",
    "Winning Clover 5 Extreme",
    "Toxic Haze",
    "African Treasure",
    "Wild Kingdom",
    "Diamond Heart 40",
    "Lux Roulette",
    "Book of Luxor Double",
    "Bikini Dice",
    "Simply Sevens",
    "Dice Wild Lines",
    "Fortune Clover 5",
    "Wild Clover 40",
    "El Grande Toro",
    "Twenty Dice",
    "Twenty Fruits",
    "Wild Cash 50",
    "Wild West",
    "Fire Clover 40",
    "Star Gems",
    "Vintage Fruits 40",
    "Amazing Joker",
    "Giga Hot 40",
    "Crystal Hot 40 Max",
    "Turbo Hot 100",
    "Fruity Win 40",
    "Very Hot 20",
    "Reel Dice",
    "Vegas Dice",
    "Roulette",
    "Jolly Poker"
],
      "gamebeat": [
    "Fortune Wild",
    "Fortune Five",
    "Fortune Three",
    "PIN-UP Fortune Double",
    "Kawaii Cafe",
    "Juicy Do Five",
    "Juicy Do Three",
    "STOLBIK777",
    "Buffalo Gold Canyon",
    "Max Miner",
    "Fortune Five Double",
    "Buffalo Dale: GrandWays",
    "Fortune 27 ways",
    "Fortune Three XMAS",
    "Sea Secret",
    "Odins Tree",
    "Buffalo Trail",
    "Frog Space Program",
    "Fortune Five 20 Lines",
    "Fruitfellas: Fortune Wheel",
    "Wolf of Wild Street",
    "Giggly Greedy Story",
    "Conquest Era",
    "Xiaos Treasures",
    "WildStock",
    "Tritons Realm",
    "Fruitfellas Xmas Wheel",
    "Totem de Oro",
    "Fortune Christmas Wild",
    "Capy Park",
    "Wolf of Xmas Street",
    "Sweet Bazaar",
    "Spin 4 Dead",
    "Clint West Wild",
    "Throne of Camelot",
    "Ganesha Legends",
    "Book of Ancients",
    "Slotout",
    "Witch Treasures",
    "Dangerous Monster",
    "Raging Lion"
],
      "fugaso": [
"Inferno Fireballs: RUNNING WINS",
    "Mexican Coins: CASH UP",
    "Jewel Sea Pirate Riches",
    "Tropical Gold",
    "Striking Diamond: RUNNING WINS",
    "Moon Of Ra: Running Wins",
    "Inferno Diamonds 100",
    "Fruits Royale",
    "Egypt Coin Link: Running Wins",
    "Diamond Blitz 100",
    "Fruits Royale 100",
    "Sugar Paradise",
    "Fruits Royale 5",
    "Striking Coin Link: RUNNING WINS",
    "Midas Links: Running Wins",
    "Xmas Royale",
    "Inferno 777 Re-spins",
    "Into The Jungle Bonus Buy",
    "Super Santa Link: RUNNING WINS",
    "Coin Rush: RHINO RUNNING WINS",
    "Power Wildz: Fruit Saga",
    "Hit The Diamond",
    "EGYPT LINKS: RUNNING WINS",
    "Striking Diamond Link: RUNNING WINS",
    "Inferno Devil 100",
    "Pop&Drop",
    "Fortune Coin Link: RUNNING WINS",
    "City Pop: Hawaii RUNNING WINS",
    "9 DRAGON BALLS: CASH UP",
    "Moon Of Egypt: RUNNING WINS",
    "Book Of Plutus",
    "TRINITY GOLD LINK: RUNNING WINS",
    "Power Boost: Money Express",
    "Trump It Coin Link: RUNNING WINS",
    "Rising Riches Link: RUNNING WINS",
    "Deluxe Fruits 100",
    "Vegas Starstruck: RUNNING WINS",
    "Mega Rich Fruits",
    "Sugar Drop",
    "Coin Rush: Elephant Strike - Running Wins",
    "Power Coin: TRINITY SERIES",
    "Devil's Diamond Rush",
    "Cash Busters",
    "Power Boost: Buffalo Express",
    "Xmas Coins: Running Wins",
    "Zeus Power Link: RUNNING WINS",
    "Thor Power Link: RUNNING WINS",
    "Fat Mama's Wheel",
    "Diamond Blitz 40",
    "Stoned Joker 5",
    "Magic Spinners",
    "Thunderbolt Coin Link: RUNNING WINS",
    "Almighty Hot Wins",
    "Clash Of Gods",
    "INFERNO FIREBALLS 2: RUNNING WINS",
    "Hercules Power Wild",
    "Mexican Mania: Hot Bonus",
    "Xmas Royale 100",
    "Book Of Tattoo 2",
    "Sweet Flips Sugar",
    "Lil Santa",
    "Stoned Joker",
    "Arctic Coins: RUNNING WINS",
    "Book Of Anime",
    "Coin Rush: Gorilla Boost RUNNING WINS",
    "Into The Jungle",
    "The Mummy Win Hunters",
    "Santa's Jingle Wheel",
    "Inferno Diamonds",
    "Thunder Wolf Link: RUNNING WINS",
    "Sugar Drop XMAS",
    "Fortune Circus",
    "Lil' Santa Bonus Buy",
    "King Of The Ring",
    "Magnify Man",
    "The Mummy Win Hunters EPICWAYS"
],
      "quickspin": [
"Eastern Emeralds Megaways",
    "Big Bad Wolf Megaways",
    "Sakura Fortune 2",
    "Sakura Fortune",
    "Panther’s Reign",
    "Big Bad Wolf",
    "Dog Town Deal",
    "Book of Duat",
    "High Street Heist",
    "Cash Truck",
    "Warp Wreckers Power Glyph",
    "Raven Rising",
    "Azticons Chaos Clusters",
    "Flip Royale",
    "Brooklyn Bootleggers",
    "Slugger Time",
    "Sticky Bandits Trail of Blood",
    "Big Bad Wolf Christmas Special",
    "Beastwood",
    "Candy Glyph",
    "Feasting Fox",
    "Cash Truck 2",
    "Book Of Yuletide",
    "Brawlers Bar Cash Collect",
    "Sakura Fortune Epic Bloom",
    "Reel Nightmare",
    "Shields of Lambda",
    "Cash Truck Xmas Delivery",
    "Big Bad Wolf: Pigs of Steel",
    "Scatter Monsters",
    "Golden Glyph 3",
    "Wild Harlequin",
    "Sticky Bandits Unchained",
    "Pineapple Crush",
    "Epic Fish Adventure",
    "Crystal Queens Coins",
    "Spinions X-mas Party",
    "Hammer of Vulcan",
    "Catrina's Coins",
    "Artemis vs Medusa",
    "Betty Bonkers",
    "Golden Glyph 2",
    "Dinosaur Rage",
    "Book of Inferno",
    "Reno 7's",
    "Sticky Bandits 3: Most Wanted",
    "Pearl o Plinko – Mermaid Cove",
    "Mine & Melt",
    "Titan Thunder: Wrath of Hades",
    "Adventures Beyond Wonderland Magical Maze",
    "Guardian of Athens",
    "Temple of Paw",
    "Crystal Prince",
    "Spinions Game Day",
    "Primal Spirits",
    "Vampire Senpai",
    "Cabin Crashers",
    "Wild Luchador",
    "Midas Coins",
    "Sevens High Ultra",
    "Loco the Monkey",
    "Crown of Valor",
    "Ghost Glyph",
    "Blue Fortune",
    "Sinbad",
    "Big Bot Crew",
    "Eastern Emeralds",
    "Ivan and the Immortal King",
    "Polar Paws",
    "Cash Truck 3 Turbo",
    "Crystal Queen",
    "Divine Dreams",
    "Goldilocks",
    "Joker Strike",
    "Sticky Bandits",
    "The Grand",
    "Skulls UP!",
    "Ark of Mystery",
    "Hall of the Mountain King",
    "Tales of Dr. Dolittle",
    "Golden Glyph",
    "Prime Zone",
    "Wild Cauldron",
    "Dragon Shrine",
    "Dwarfs Gone Wild",
    "King Colossus",
    "Mayana",
    "Mighty Arthur",
    "Northern Sky",
    "Phoenix Sun",
    "Pied Piper",
    "Pirate's Charm",
    "Wild Chase: Tokyo Go",
    "Rapunzel's Tower",
    "Spinions",
    "Ticket to the stars",
    "Tiger's Glory",
    "Volcano Riches",
    "Wins of Fortune",
    "Nero's Fortune",
    "Diamond Duke",
    "Wild Tome of the Woods",
    "Sticky Bandits: Wild Return",
    "Fairy Gate",
    "Gold Lab",
    "Hot Sync",
    "Illuminous",
    "Leprechaun Hills",
    "Razortooth",
    "Second Strike",
    "Sevens High",
    "The Wild Chase",
    "Treasure Island",
    "Durian Dynamite",
    "Arcane Gems"
],
      "wizard": [
        "Teddy's Tavern",
    "12 Super Hot Diamonds",
    "Dragon's of the North MegaWays",
    "Surtr's Fury",
    "Awww, So Cute!",
    "Cakes of Fortune",
    "Digipays",
    "12 Super Hot Diamonds Extreme!",
    "Incan Treasures",
    "Madame Voodoo",
    "The Funky Boombox",
    "Chicken Burst",
    "Wild Fruit Super Wheel",
    "Captains of the Coast 2",
    "Fortune Tree of Wealth",
    "Ice Ice Hockey",
    "Spirit Of Mustang",
    "Treasure Temple",
    "Amun Ra - King of the Gods",
    "Princess Celina and the Frog",
    "Dreamy Divas",
    "Alice Mega Riches",
    "Scrolls of Aphrodite",
    "Piggi Bank",
    "Treasures of The Count",
    "Lucky Lamp",
    "Fisherman’s Bounty",
    "Sultan's Palace Fortune",
    "Carnival of Calacas",
    "Bier Haus Riches",
    "Wildwood Buffalo",
    "Santa's Fortune",
    "Wild West Ways",
    "Santa Bonanza",
    "Thor's Hammer Strike",
    "Sizzling Mystery",
    "Jingle Wins",
    "La Mafia Heist",
    "Golden Elk",
    "Grand Pepper Party",
    "Gods of Kemet",
    "Mammoth Mayhem",
    "Catchin’ Fortunes",
    "Super Hot Joker",
    "Tiger Emperor",
    "Alice in Vegasland",
    "Wild Wild Pistols",
    "Towers Of Olympus",
    "Boitatá The Fire Guardian",
    "Fisherman’s Bounty Deluxe",
    "Hot Hot 777",
    "Wolf Riches",
    "Bring In The Fish",
    "Flamin'7s",
    "Captains of the Coast",
    "Wild Wild Wynmor",
    "Majestic North",
    "Coin Fever",
    "Stallion Fortunes",
    "Phoenix Kingdom",
    "Book of Enternal Romance",
    "Vampire’s Secret Treasures",
    "King Koko's Quest",
    "Emeralds of Oz",
    "Froots",
    "Alice Riches",
    "The Good, the Bad & The Wild",
    "Book of Enchantments",
    "Cup Glory",
    "Sweet Feast",
    "Goddess Of Fortunes",
    "Jade King",
    "Dragons of the North Deluxe",
    "Rumble Rhino MEGAWAYS",
    "Tiki Magic",
    "Power Strike Super Spin",
    "Aesir Treasures",
    "Bier Party",
    "Unchain the Dragons",
    "Lucky Keno",
    "Wild Candy",
    "King of the Trident Deluxe",
    "The Secret Order",
    "Gold's Guardian",
    "Mystery Fox Christmas Party",
    "Phoenix Gold",
    "Book of Itza",
    "Jackpot Fortunes",
    "Hot Wild 7s",
    "Grand Loot",
    "Epic Riches",
    "The Thunderer",
    "The Prancing Pony",
    "Force of the Gods",
    "Wild Fortunes",
    "Faith",
    "Magic Baccarat",
    "Fruity Friends",
    "Fortune Dragons",
    "Rio Fever",
    "Cops And Robbers",
    "Aloha Fortune",
    "Titans Riches",
    "Las Cucas Locas",
    "Torro's Gold",
    "The Alchemist",
    "Spin N' Hit",
    "Bubble Hits",
    "Joker Joker",
    "Amazing Riches",
    "Fruit Basket",
    "Luxor Scratch",
    "Dragon Scrolls",
    "Fire Vs. Ice",
    "XO Manowar",
    "Chitty Bang",
    "Goddess Of The Moon",
    "Tokyo Nights",
    "Jonny Ventura And The Eye Of Ra",
    "Santa's Workshop",
    "BloodShot Rising Spirit",
    "BloodShot",
    "Mystery Fox",
    "Barn Ville",
    "Mega Love",
    "Rio Bingo",
    "Pot O'Gold",
    "Ocean Fortune",
    "Zodiac Fortune",
    "Cash Cuisine",
    "Zombies Gone Wild",
    "Royal Charm",
    "European Roulette Min: 0.10c",
    "European Roulette High Stakes",
    "Pets 94",
    "Bai She Zhuan",
    "World Cup Keno",
    "Dragons of the North",
    "Goldorado",
    "Wild Cherry",
    "Luxor",
    "Fur Balls",
    "Parrot's Gold",
    "Viking Glory",
    "Sweetie Land",
    "Fruit Abduction",
    "Magical Forest",
    "Fish and Chips",
    "I Love Christmas",
    "Lucky Vegas",
    "Jack In The Box",
    "Xi You Ji",
    "King of the Trident",
    "Mystic Manor",
    "Jack’s Treasure",
    "Gems and Riches"
],
      "voltent" [
 "25 Coins",
  "12 Bells",
  "16 Coins",
  "20 Coins",
  "36 Coins",
  "9 Coins",
  "Hot Slot: 777 Coins",
  "Mighty Symbols: Crowns",
  "9 Coins Grand Diamond Edition",
  "Power of Gods: Medusa",
  "Book of Faith",
  "Mighty Wild: Panther Halloween Edition",
  "Hot Slot: 777 Coins Extremely Light",
  "Football Mania Deluxe",
  "Mighty Wild: Panther",
  "Mighty Fish Blue Marlin",
  "9 Bells",
  "9 Lions",
  "Hot Slot: Magic Pearls",
  "12 Coins Grand Gold Edition",
  "24 Coins",
  "9 Coins Extremely Light",
  "Butterfly Lovers",
  "30 Coins",
  "Jacks Ride",
  "Mighty Symbols: Diamonds",
  "Lucky Fortune",
  "Hot Slot: 777 Cash Out Extremely Light",
  "Mighty Wild: Panther Grand Diamond Edition Love the Jackpot",
  "9 Coins Grand Diamond Xmas",
  "Hot Slot: Great Book Of Magic",
  "Power of Gods: Valhalla",
  "12 Coins",
  "16 Coins Grand Gold Edition",
  "Mighty Wild: Panther Grand Gold Edition",
  "20 Coins Halloween Jackpots",
  "12 Coins Grand Diamond Edition",
  "Hot Slot: 777 Stars",
  "Moon Of Fortune",
  "Mighty Wild: Jaguar",
  "16 Coins Xmas",
  "Mighty Wild: Panther Xmas",
  "Power of Gods: Hades Love the Jackpot",
  "36 Coins Halloween Jackpots",
  "9 Coins Love the Jackpot",
  "Hot Slot: 777 Cash Out Xmas",
  "16 Coins Grand Platinum Edition",
  "Mighty Wild: Panther Grand Platinum Edition Santas Jackpots",
  "Hot Slot: 777 Crown Extremely Light",
  "Burning Sun Easter",
  "20 Coins Grand Gold Edition",
  "9 Bells Love the Jackpot",
  "Black Horse Cash Out",
  "Mighty Wild: Panther Grand Diamond Edition",
  "Mighty Symbols Jokers Santas Jackpots",
  "Hot Slot: 777 Cash Out Grand Gold Edition",
  "Los Muertos 2",
  "Hot Slot: 777 Rubies Extremely Light",
  "16 Coins Love the Jackpot",
  "16 Coins Halloween Edition",
  "Mighty Wild: Panther Grand Platinum Edition",
  "Magic Spins Love the Jackpot",
  "Sizzling Eggs Halloween Edition",
  "25 Coins Santas Jackpots",
  "25 Coins Grand Gold Edition",
  "9 Coins Grand Diamond Love the Jackpot",
  "Prosperity Reels",
  "Burning Sun Extremely Light",
  "Hot Slot: 777 Cash Out Halloween Edition",
  "9 Lions Hold the Jackpot Halloween Jackpots",
  "15 Coins Grand Gold Edition",
  "Mighty Wild: Panther Grand Diamond Edition Halloween Jackpots",
  "36 Coins Love the Jackpot",
  "Mighty Wild: Jaguar Love the Jackpot",
  "15 Coins: Grand Platinum Edition",
  "9 Lions Hold the Jackpot",
  "Hot Slot: 777 Cash Out Grand Platinum Edition",
  "Hot Slot: 777 Cash Out Grand Diamond Edition",
  "Night Club 81",
  "Hot Slot: 777 Stars Extremely Light",
  "16 Coins Grand Gold Edition Santas Jackpots",
  "Burning Sun",
  "Mighty Wild: Panther Easter",
  "25 Coins Easter",
  "Mighty Symbols: Sevens",
  "Power of Gods: Valhalla Extremely Light",
  "20 Coins Score The Jackpot",
  "Hot Slot: 777 Cash Out Easter",
  "30 Coins Score the Jackpot",
  "36 Coins Score the Jackpot",
  "One Coin",
  "9 Coins Grand Platinum Edition Score the Jackpot",
  "20 Coins Easter",
  "12 Coins: Grand Platinum Edition",
  "Mighty Symbols: Jokers",
  "Jelly Reels Xmas Edition",
  "9 Coins Xmas",
  "Dwarfs Fortune",
  "9 Burning Stars",
  "9 Coins Grand Gold Edition",
  "9 Coins Grand Platinum Edition",
  "Jack on Hold",
  "Jelly Reels",
  "9 Coins 1000x Edition",
  "Dwarfs Fortune Easter",
  "Hot Slot: 777 Cash Out",
  "Power of Sun: Svarog",
  "Sizzling Kingdom: Bison",
  "Choco Reels Easter",
  "Sizzling Eggs Extremely Light",
  "Hot Slot: 777 Crown",
  "Magic Spins Xmas Edition",
  "Hot Slot: Magic Bombs",
  "Hot Slot: Mystery Jackpot Joker",
  "9 Coins Halloween",
  "Larry the Leprechaun",
  "Magic Spins",
  "Mystery Kingdom: Mystery Bells",
  "Power of Gods: Medusa Easter",
  "Burning Stars 3 Xmas",
  "Larry the Leprechaun Easter",
  "Sizzling Eggs",
  "Power of Gods: Medusa Extremely Light",
  "9 Burning Dragons",
  "Magic Eggs",
  "Burning Stars 3",
  "15 Coins",
  "Cube Mania",
  "Fortune Reels",
  "Neon City",
  "9 Lions Xmas Edition",
  "Midnight in Tokyo",
  "Cube Mania Deluxe",
  "Sun Of Fortune Xmas Edition",
  "Prosperity Pearls",
  "Power of Gods: Egypt",
  "Sizzling Moon",
  "Sizzling Bells",
  "Hot Slot: 777 Rubies",
  "Welcome To Hell 81",
  "Magic Of The Ring",
  "Reel Hero",
  "Reel Joke",
  "Lucky 9",
  "Unicorn Reels",
  "Sun of Fortune",
  "Power of Gods: Hades",
  "Fruit Mania",
  "Black Horse Deluxe",
  "Dragons Lucky 8",
  "Telly Reel",
  "Gem Splitter",
  "Choco Reels",
  "Wild Jack 81",
  "Hot Party Deluxe",
  "Relic Hunters and the Book of Faith",
  "Magic Stars 9",
  "9 Tigers",
  "Clover Lady",
  "Joker Poker",
  "Turbo Poker",
  "Three Cards",
  "Magic Poker",
  "Caribbean Beach Poker",
  "Extra Bingo",
  "Bell Wizard",
  "Casino Roulette",
  "Great Book Of Magic Deluxe",
  "Black Hawk Deluxe",
  "Lucky Reels",
  "Infinity Hero",
  "Black Hawk",
  "Vegas Reels II",
  "Fire Bird",
  "Magic Hot 4 Deluxe",
  "Lucky Fish",
  "Burning Stars",
  "Back to the 70s",
  "Gold Roulette",
  "Spectrum",
  "Wild Guns",
  "BARs & 7s",
  "Fruit Mania Deluxe",
  "Corrida Romance Deluxe",
  "Fruit Fiesta",
  "Sonic Reels",
  "Highschool Manga",
  "Sizzling 777 Deluxe",
  "Fruits Go Bananas",
  "Fenix Play 27",
  "Magic Of The Ring Deluxe",
  "Highway to Hell Deluxe",
  "Lost Treasure",
  "Slot Jam",
  "Valhalla",
  "Los Muertos",
  "Golden Sphinx",
  "Triple Star",
  "KickOff",
  "Crazy Cars",
  "Hot Party",
  "Demon Jack 27",
  "Power of Gods: The Pantheon",
  "Draculas Castle",
  "Dino Reels 81",
  "Wild Jack",
  "Magic Fruits 4",
  "Jackpot Builders",
  "Turbo Play",
  "Vegas Hot",
  "Beach Party",
  "Mayan Ritual",
  "Jumping Fruits",
  "Mystery Jack",
  "Magic Fruits 81",
  "Haunted Hospital",
  "Criss Cross 81",
  "In The Forest",
  "Highway to Hell",
  "Double Tigers",
  "Corrida Romance",
  "Fenix Play",
  "Wild Girls",
  "Joker Explosion",
  "Super Hot",
  "Magic Stars",
  "Hot 777",
  "Miami Beach",
  "Juicy Reels",
  "American Poker V",
  "Good Luck 40",
  "Magic Target",
  "Win & Replay",
  "American Poker Gold",
  "Magic Hot 4",
  "Beach Party Hot",
  "Vegas Hot 81",
  "Magic Fruits 27",
  "Magic Fruits Deluxe"
],
        "egt": [
        "40 Super Hot Bell Link",
        "40 Super Hot Bell Link",
        "Flaming Hot Extreme Bell Link",
        "40 Shining Crown Bell Link",
        "40 Burning Hot 6 Reels",
        "Shining Crown",
        "100 Burning Hot",
        "20 Super Hot Bell Link",
        "Flaming Hot Bell Link",
        "Burning Hot Bell Link",
        "40 Burning Clover 6 Reels",
        "40 Burning Hot",
        "40 Super Fruits Bell Link",
        "Flaming Hot Extreme",
        "40 Shining Crown",
        "Shining Crown Bell Link",
        "40 Lucky King Bell Link",
        "Vampire Night Bell Link",
        "40 Lucky King Extreme Bell Link"
    ]
    }
  },
  "az": {
    "providers": {
      "pg-soft": [
        "Leprechaun Riches",
        "Spirited Wonders",
        "Wild Bounty Showdown",
        "Fortune Tiger",
        "Mermaid Riches",
        "Fortune Ox",
        "Hawaiian Tiki",
        "Bakery Bonanza",
        "Wild Ape #3258",
        "Fortune Rabbit",
        "Safari Wilds",
        "Mask Carnival",
        "Mafia Mayhem",
        "Gemstones Gold",
        "Rave Party Fever",
        "Lucky Clover Lady",
        "Forge of Wealth"
      ],
      "PlaynGO": [
        "Treasures of Kongar",
        "Wild Survivor",
        "Gigantoonz",
        "Legacy of Dead",
        "Rich Wilde and the Tome of Madness",
        "Idol of Fortune",
        "Leprechaun's Vault",
        "Rise of Merlin",
        "Perfect Gems",
        "Dansband Pa Turne",
        "King's Mask",
        "Cash of Command",
        "Book of Dead",
        "Cat Wilde and the Pyramids of Dead",
        "Forge of Fortunes",
        "Mount M",
        "Rocco Gallo",
        "Tales of Asgard: Loki’s Fortune",
        "Fortune Rewind",
        "DIO - Killing the Dragon",
        "Rise of Gods Reckoning",
        "Secret of Dead",
        "Beasts Of Fire",
        "Boat Bonanza Down Under"
      ],
      "spinomenal": [
        "Baba Yaga Tales",
        "Majestic Bison",
        "Majestic Claws - Wild Snow",
        "The Tricksters Treasure",
        "PIN-UP Fortune",
        "Queen Of The Forest",
        "Story Of Odin",
        "Fairytale Beauties",
        "Bavarian Riches 2",
        "PIN-UP Athenas Glory",
        "Gangsters Gold - On The Run",
        "100 Lucky PIN-UPs – Spin’O’wheel",
        "Valentine Collection 20 Lines",
        "Demi Gods V",
        "Celestial Conquest",
        "PIN-UP Book Of Demi Gods 2",
        "Book Of Savannahs Queen"
      ],
      "spribe": [
        "Mines",
        "Keno",
        "Dice",
        "MiniRoulette",
        "Goal",
        "Plinko",
        "Hotline",
        "HiLo",
        "Aviator"
      ],
      "playson": [
        "Burning Wins: classic 5 lines",
        "Thunder Coins: Hold and Win",
        "Energy Coins: Hold and Win",
        "Book of Gold: Multichance",
        "Diamond Fortunator: Hold and Win",
        "Jingle Coins: Hold and Win",
        "Luxor Gold: Hold and Win",
        "Jokers Coins: Hold and Win",
        "Buffalo Power 2: Hold and Win",
        "Burning Wins x2",
        "Sherwood Coins: Hold and Win",
        "Book del Sol: Multiplier",
        "Pirate Chest: Hold and Win",
        "Royal Coins: Hold and Win",
        "Burning Fortunator",
        "Sunny Fruits: Hold and Win",
        "100 Joker Staxx",
        "Joker Expand: 5 Lines",
        "Wolf Power: Hold and Win",
        "Fruits & Jokers: 20 lines",
        "Solar King",
        "Book of Gold: Classic",
        "Divine Dragon: Hold and Win",
        "Hot Burning Wins",
        "Book of Gold: Double Chance",
        "Eagle Power: Hold and Win",
        "Rise of Egypt",
        "5 Super Sevens & Fruits",
        "5 Fortunator",
        "Sevens&Fruits: 20 Lines",
        "Solar Temple",
        "Buffalo Power Megaways",
        "Wolf Power Megaways",
        "Legend of Cleopatra",
        "3 Fruits Win: 10 Lines"
      ],
      "nolimit": [
        "Disturbed",
        "Jingle Balls",
        "Bounty Hunters",
        "Fire In The Hole xBomb",
        "Mental",
        "The Creepy Carnival",
        "Casino Win Spin",
        "Manhattan Goes Wild",
        "Coins Of Fortune",
        "Mayan Magic",
        "Hot 4 Cash",
        "Hot Nudge"
      ],
      "gamzix": [
        "Ruby Win: Hold The Spin",
        "Japanese Coin: Hold The Spin",
        "Samba Stars: Hold the Spin",
        "Sunny Coin 2: Hold The Spin",
        "Really Hot Flaming Edition",
        "Coin Win: Hold The Spin",
        "Ultra Luck",
        "3x3 Hold The Spin",
        "Pilot",
        "Burning Power",
        "PIN-UP Coin",
        "Sticky Coin: Hold the Spin",
        "Pilot Cup",
        "Pilot Coin",
        "Joker Splash",
        "Dice: Hold The Spin",
        "40 Chilli Fruits Flaming Edition",
        "40 Sweet Fruits",
        "Locky Fruits: Hold the Spin",
        "The Hottest Game", 
        "Go Wild",
        "Book Of Symbols",
        "Snow Coin: Hold The Spin",
        "GG Coin: Hold The Spin",
        "Buffalo: Ice Hold The Spin",
        "Dogs and Tails",
        "Wolf Story",
        "Dice: Hold The Spin",
        "Santa Sphere: Hold The Spin",
        "Happy Rabbit: 27 Ways",
        "Bonanza Donut Xmas",
        "Bonanza Donut",
        "Really Hot",
        "Patrick’s Coin: Hold The Spin",
        "Billie Wild",
        "Spooky Coin: Hold The Spin",
        "3X3: Hell Spin",
        "Hot Love",
        "Fruit Story: Hold the Spin",
        "Egypt Sphere: Hold the Spin",
        "Juicy Win: Hold The Spin",
        "40 Chilli Fruits",
        "Royal Chip",
        "Fruit Story",
        "Won Hundred",
        "Buffalo Coin: Hold The Spin",
        "Hot Patrick",
        "Book of Zulu",
        "Gold Mania",
        "Olympus of Luck: Hold the Spin",
        "Really Hot 2",
        "Book of Cairo",
        "Really Easter",
        "3X3: 27 Ways"
      ],
      "netgame": [
        "Royal Fruits 5: Hold n Link",
        "Frog Princess",
        "Cactus Riches: Cash Pool",
        "Pompeii Gold: Rapid Link",
        "Rich Piggies: Bonus Combo",
        "Hot Cash: Hold ‘n’ Link",
        "Wolf Reels Rapid Link",
        "Big Catch Bonanza",
        "Elephants Gold: Buy Bonus Combo",
        "Wild Buffalo: Rapid Link",
        "Wild Buffalo Hold 'N' Link",
        "Wild Buffalo Fortune Wheel",
        "Wild Buffalo",
        "Fruit Burst",
        "Golden Tree"
      ],
      "1spin4win": [
        "Book of Wild",
        "Lucky 10 Bells",
        "Coinsn Fruits Spins",
        "Mega Lucky 576",
        "Cashn Fruits Fortune 100",
        "Lucky 432 Ways",
        "Coinsn Fruits Spins",
        "PIN-UP CashnFruits 100",
        "Cash The Gold",
        "Mega Lucky 576",
        "Cashn Fruits 243",
        "Booming Fruits 243",
        "Mega Lucky 243",
        "Mega Booming Fruits",
        "Mega Lucky 100",
        "PIN-UP Fruits 243",
        "Cashn Fruits 100",
        "Allways Lucky Pot"
      ],
      "amusnet": [
        "Shining Crown",
        "Ultimate Hot",
        "Fruity Time",
        "Flaming Hot 6 Reels",
        "Kamakura",
        "Candy Palace",
        "Mighty Sparta",
        "Supreme Hot",
        "Vampire Bites",
        "Extra Crown",
        "Power Hot",
        "Phoenix Star",
        "Lucky Wood",
        "Game of Luck",
        "More Lucky & Wild",
        "Golden Coins",
        "Bulky Fruits",
        "100 Bulky Fruits",
        "Wild Goals"
      ],
        "amatic": [
        "Lucky Joker 10 Extra Gifts",
        "All Ways Hot Fruits",
        "Hot Fruits 100",
        "Lady PIN-UPs 100",
        "Lucky Joker 100",
        "Lucky Piggies 2 Hold&Win",
        "Book Of Aztec",
        "Grand Fruits",
        "Lucky Joker 40",
        "Fruit Box",
        "Joker X",
        "All Ways Hottest Fruits",
        "Hot Fruits 20 Cash Spins",
        "Lucky Joker 10",
        "Blazing Bells 20",
        "Blazing Coins 100",
        "Hot Fruits 27"
      ],
      "novomatic": [
    "Treasure Jewels",
    "5 Sevens Hold & Win",
    "Sizzling Hot",
    "Book of Ra Deluxe Buy Bonus",
    "Bananas Go Bahamas",
    "20 Mega Hotfire",
    "10 Devils Hotfire",
    "5 Super Clover",
    "Banana Splash",
    "Book Hotfire",
    "Book of Luck",
    "Ultra Hotfire",
    "Sizzling Gems",
    "Book Hotfire Buy Bonus",
    "Christmas Boom",
    "The Money Game",
    "Scarab Fortunes",
    "50 Jokers Hotfire",
    "Plenty on Twenty Hot",
    "Pharaohs Gold II",
    "Jackass Gold Hold & Win Buy Bonus",
    "Just Jewels Deluxe",
    "Faust Buy Bonus",
    "Always Hot",
    "Plenty of Fruit 40",
    "Supra Hot",
    "Royal Treasures",
    "Plenty of Fruit 20 Hot",
    "King of Cards",
    "The Magic Flute",
    "5 Sevens Hold & Win Christmas",
    "Queen of Hearts Deluxe",
    "Wings of Fire",
    "Gorilla",
    "Olivers Bar",
    "Hot Chance",
    "50 Jokers Christmas",
    "Silver Fox",
    "Flame Dancer",
    "Indian Spirit",
    "Gryphons Gold",
    "Aztec Eclipse Hold & Win",
    "Mermaids Pearl",
    "Sharky",
    "Million Dollar Heist Xtreme",
    "Book Hotfire Multichance Buy Bonus",
    "Katana",
    "River Queen",
    "Fortune God",
    "Chicago",
    "Chip Runner",
    "Riches of India",
    "5 Sevens",
    "Golden Ark",
    "Mystic Bull",
    "Magic Money",
    "The Euro Game",
    "Million Dollar Heist",
    "Book Hotfire Multichance",
    "Gold Fever",
    "5 Sevens Dice",
    "Macarena"
  ],
      "zeusplay": [
  "Great Buffalo",
  "Diamond Freeze",
  "40 Flaming Lines",
  "Nine Dragon Coins",
  "Fifteen Dragon Coins",
  "Diamonds Fortune",
  "Butterfly Hot 10",
  "Hot 27 Lines",
  "Hot Diamonds 5",
  "Hot Diamonds 20",
  "Hot Diamonds 40",
  "Royal Jewels",
  "The Divine 12th",
  "The Emperors Curse",
  "Amuns Book HD",
  "Arabian Dream Remastered",
  "Wilds and Pirates",
  "Don Mafioso",
  "The Zodiac 12 Water Edition",
  "A Fistful of Coins",
  "Disco Fever",
  "Abby And The Witch",
  "Haunted Walker",
  "Bubbles And Pearls",
  "Hot 20 Deluxe",
  "Fire 20 Deluxe",
  "Fairys Golden Path",
  "Captain Nelson Deluxe",
  "Dice Tronic",
  "Hot 5 Deluxe",
  "Dice Tronic X",
  "Extra Super Hot Bbq",
  "Farm Madness",
  "Hot Diamonds 20 Dice",
  "Dice Tronic Xl",
  "Infinium",
  "Hot Diamonds 40 Dice",
  "Lady Of The Forest",
  "Golden Dice 3",
  "Mad Cubes 25",
  "Le Mystere Du Prince",
  "Mad Cubes 50",
  "Magic Charm",
  "The Explorers Quest",
  "Page Of Fortune Deluxe",
  "Snake Eyes",
  "Star Frenzy",
  "Wild Charger",
  "The Lost Temple",
  "Super Hot Bbq",
  "Trojan Horse Tiny Heroes"
],
"bgaming": [
  "Wild Cash",
  "Lady Wolf Moon",
  "Aztec Clusters",
  "Burning Chilli X",
  "Fruit Million",
  "Lucky Lady PIN-UP",
  "Bonanza Billion",
  "Luck & Magic",
  "Lucky Ladys Clover",
  "Space XY",
  "All Lucky Clovers 100",
  "Diamond of Jungle",
  "Wild Tiger",
  "Wild West TRUEWAYS",
  "Aztec Magic Deluxe",
  "All Lucky Clovers",
  "Miss Cherry Fruits",
  "Halloween Bonanza",
  "Aviamasters",
  "Alien Fruits FS",
  "PIN-UP Bonanza",
  "Clover Bonanza",
  "Gemhalla",
  "Book Of Cats",
  "Aztec Magic Megaways",
  "Hottest 666",
  "Panda Luck",
  "Snoop Dogg Dollars",
  "Elvis Frog in Vegas",
  "Fishing Club",
  "Lucky Farm Bonanza",
  "Merge Up",
  "Gold of Minos",
  "Mechanical Clover",
  "Mummys Gold",
  "Joker Queen",
  "Slot Machine",
  "Big Atlantis Frenzy",
  "Mice & Magic Wonder Spin",
  "Book of Kemet",
  "PIN-UP Million",
  "Lucky Crew",
  "Aztec Magic Bonanza",
  "Miss Cherry Fruits Jackpot Party",
  "Lucky Dragon MultiDice X",
  "Wild Cash Dice",
  "Domnitors Treasure",
  "Gemza",
  "Road 2 Riches",
  "Voodoo People",
  "Wild Moon Thieves",
  "Gift Rush",
  "Dragon Age Hold & Win",
  "Candy Monsta",
  "Lady Wolf Moon Megaways",
  "Gold Rush with Johnny Cash",
  "All Lucky Clovers 40",
  "Beast Band",
  "Penny Pelican",
  "Potion Spells",
  "WBC Ring of Riches",
  "Grand Patron",
  "Winter Fishing Club",
  "Gangsterz",
  "Wild Cash x9990",
  "OOF The Goldmine Planet",
  "Tramp Day",
  "Wild Chicago",
  "Lucky 8 Merge Up",
  "Savage Buffalo Spirit Megaways",
  "Hit The Route",
  "Fortuna TRUEWAYS",
  "Johnny Cash",
  "Chicken Rush",
  "PIN-UP Soccermania",
  "Bone Bonanza",
  "God of Wealth Hold And Win",
  "Book of Panda Megaways",
  "Sweet Rush Megaways",
  "Wild Heart",
  "Dragons Crash",
  "Lucky Oak",
  "Capymania Green",
  "Keepers Of The Secret",
  "Krakens Hunger",
  "Catch the Gold Hold and Win",
  "Pop Zen",
  "Royal Fruits MultiLines",
  "Carnival Bonanza",
  "Forgotten",
  "Easter Heist",
  "Four Lucky Clover",
  "Maneki 88 Fortunes",
  "Aztecs Claw Wild Dice",
  "Savage Buffalo Spirit",
  "Royal High-Road",
  "Scratch Alpaca Silver",
  "Haunted Reels",
  "Hot Chilli Bells",
  "Gold Magnate",
  "Disco Party",
  "Tile Master",
  "Joker’s Million",
  "Dice Clash",
  "Golden Pride",
  "Mine Gems",
  "Catdiana",
  "Capymania Orange",
  "Monster Hunt",
  "Capymania Yellow",
  "Book Of Cats Megaways",
  "Robospin",
  "Scratch Alpaca Bronze",
  "Scratch Alpaca Gold",
  "Dice Bonanza",
  "Ice Scratch Bronze",
  "Forty Fruity Million",
  "Maneki 88 Gold",
  "Beer Bonanza",
  "Sakura Riches 60",
  "Ice Scratch Gold",
  "Elvis Frog Trueways",
  "Gift X",
  "Aztec Magic",
  "Rotating Element",
  "Lucky Ducky",
  "Ice Scratch Silver",
  "Train to Rio Grande",
  "Top Eagle",
  "Dice Million",
  "Street Power",
  "Alien Fruits 2",
  "Secret Bar Multidice X",
  "Plinko 2",
  "Aloha King Elvis",
  "Lucky Dama Muerta",
  "Dig Dig Digger",
  "Dragon’s Gold 100",
  "3 Kings Scratch",
  "Limbo XY",
  "Easter Plinko",
  "Plinko XY",
  "Minesweeper XY",
  "Rocket Dice XY",
  "Heads and Tails XY",
  "Luck & Magic Scratch",
  "Deep Sea",
  "Minesweeper",
  "Avalon: The Lost Kingdom",
  "Journey Flirt",
  "Book of Pyramids",
  "Hawaii Cocktails",
  "Jogo Do Bicho",
  "Scratch Dice",
  "All Lucky Clovers 20",
  "All Lucky Clovers 5",
  "Spin and Spell",
  "Desert Treasure",
  "Hello Easter",
  "Rocket Dice",
  "Fantasy Park",
  "Fire Lightning",
  "Lucky Blue",
  "Platinum Lightning",
  "Platinum Lightning Deluxe",
  "Princess of Sky",
  "West Town",
  "Brave Viking",
  "Cherry Fiesta",
  "Crazy Starter",
  "Domnitors",
  "French Roulette",
  "Heads and Tails",
  "Multihand Blackjack",
  "American Roulette",
  "Multihand Blackjack Pro",
  "European Roulette"
],
      "fazi": [
    "Very Hot 5",
    "Turbo Stars 40",
    "Fruits and Stars",
    "Crystal Hot 40",
    "King of Thunder",
    "Hot Stars",
    "Pyramid",
    "Christmas Presents",
    "Pirates",
    "Book of Spells Deluxe",
    "Twinkling Hot 5",
    "Retro 7 Hot",
    "Santas Presents",
    "Triple-Hot",
    "Turbo Hot 40",
    "Fruit Island Christmas",
    "Clover Coin",
    "Rainbow Sevens",
    "Crystal Hot 40 Christmas",
    "Book of Spells",
    "Fruits and Stars 40 Christmas",
    "Bonus Bells",
    "Fashion Night",
    "Mayans Battle",
    "Heating Ice Deluxe",
    "Starlight",
    "Wild Hot 40",
    "Golden Explosion",
    "Lady Triple Fortune",
    "Very Hot 5 Extreme",
    "Wild Forties Xmas",
    "Fortune Clover X2",
    "Joker Triple Double",
    "Dice Machine",
    "Book of Bruno",
    "Twinkling Hot 40",
    "Bikini Fruits",
    "Thunder Fruits",
    "20 Hot Strike",
    "Fruits and Stars Christmas",
    "Crowns and Stars",
    "Clover Royale",
    "Lollas World Christmas",
    "Hot Rush Stars Deluxe",
    "Viking Gold",
    "Hot Rush Crown Burst",
    "Turbo Hot 40 Christmas",
    "Cosmic Sevens",
    "20 Hot Strike Jackpot",
    "Special Fruits",
    "Diamond Heart x2",
    "Very Hot 40",
    "Eternal Hearts 10",
    "Golden Crown Christmas",
    "Hearts & Stars",
    "Hot Stars Christmas",
    "Jolly Presents",
    "Retro 7 Hot Christmas",
    "Lava Diamonds Christmas",
    "Bonus Epic Crown",
    "Aloha Charm",
    "Majestic Crown 10",
    "Triple Fields of Luck",
    "Wild Craps",
    "Twinkling Hot 40 Christmas",
    "Very Hot 40 Christmas",
    "Golden Crown 40",
    "Wizard",
    "Wild Hot 40 Free Spins",
    "Katanas of Time",
    "Very Hot 5 Christmas",
    "Epic Fire 40",
    "Templars Quest",
    "Pixel Hot 40",
    "Fruits and Stars 40",
    "Mystery Joker Hot",
    "Wild Hot 40 Christmas",
    "Crystals of Magic",
    "Dolphins Shine",
    "Space Guardians",
    "Book of Spells 2",
    "Turbo Hot 80",
    "Fire Clover 5",
    "Fear of Dark",
    "Wild Crown 10",
    "Jazzy Fruits",
    "Wild Paradise",
    "Money 5",
    "Fruit Island",
    "Golden Crown",
    "Havana Dice",
    "Epic Clover 40",
    "Diamond Heart 5",
    "Mayan Coins",
    "Wild Hot 40 Blow",
    "Wild 27",
    "The Crown Fruit",
    "Casino Fruits",
    "Fire Dice 5",
    "Crystal Hot 40 Free Spins",
    "Chilli Respin",
    "Wild Dice 40",
    "Mega Hot 10",
    "Postman",
    "Deep Jungle",
    "Fruity Hot 5",
    "Gold Line Dice",
    "20 Mega Flames",
    "Clovers & Stars",
    "Buffalo Dice",
    "Action Hot 20",
    "Gold Line",
    "Wild Lucky Clover",
    "10 Jingle Fruits",
    "Action Hot 40",
    "81 Vegas Crown",
    "Forest Fruits",
    "Wild Lucky Clover 2",
    "40 Dice Flames",
    "HEAT Classic 5",
    "40 Mega Flames",
    "Very Hot 40 Respin",
    "Turbo Fire",
    "Wild 81",
    "Book of Ibis",
    "Sticky Hot",
    "Lollas World",
    "Crystal Hot 40 Deluxe",
    "Crystal Jewels",
    "Winning Clover 5",
    "Star Runner",
    "Heating Fruits",
    "Dice Double",
    "Crystal Joker Hot",
    "Blow Fruits 40",
    "Turbo Stars 10",
    "Double Clover Fire",
    "Dashing Hot 5",
    "Fruity Win 20",
    "Wild Heat 40",
    "Mega Cubes Deluxe",
    "Football Victory",
    "Mega Hot 20",
    "Crystal Hot 100",
    "20 Dice Flames",
    "Summer Rush",
    "Mystic Jungle",
    "Wild Dice 10",
    "Fortune Parrot",
    "Mini Mega Cash",
    "VIP Roulette",
    "Wild Heart 5",
    "Lava Dice",
    "Epic Clover 100",
    "Spooky Spins",
    "Fluo Dice 5",
    "Fortune Clover 40",
    "Majestic Crown 20",
    "Cash Bells 40",
    "Wild Diamond 10",
    "Epic Crown 5",
    "Power of the Great",
    "Heating Ice",
    "Great Whale",
    "Da Vincis Fruits",
    "Winning Stars",
    "Island Respins",
    "Fruit Magic",
    "Fire Dice 40",
    "Monsters",
    "Lost Book",
    "Crystal Hot 80",
    "Money Standard",
    "Winning Clover 5 Extreme",
    "Toxic Haze",
    "African Treasure",
    "Wild Kingdom",
    "Diamond Heart 40",
    "Lux Roulette",
    "Book of Luxor Double",
    "Bikini Dice",
    "Simply Sevens",
    "Dice Wild Lines",
    "Fortune Clover 5",
    "Wild Clover 40",
    "El Grande Toro",
    "Twenty Dice",
    "Twenty Fruits",
    "Wild Cash 50",
    "Wild West",
    "Fire Clover 40",
    "Star Gems",
    "Vintage Fruits 40",
    "Amazing Joker",
    "Giga Hot 40",
    "Crystal Hot 40 Max",
    "Turbo Hot 100",
    "Fruity Win 40",
    "Very Hot 20",
    "Reel Dice",
    "Vegas Dice",
    "Roulette",
    "Jolly Poker"
],
      "gamebeat": [
    "Fortune Wild",
    "Fortune Five",
    "Fortune Three",
    "PIN-UP Fortune Double",
    "Kawaii Cafe",
    "Juicy Do Five",
    "Juicy Do Three",
    "STOLBIK777",
    "Buffalo Gold Canyon",
    "Max Miner",
    "Fortune Five Double",
    "Buffalo Dale: GrandWays",
    "Fortune 27 ways",
    "Fortune Three XMAS",
    "Sea Secret",
    "Odins Tree",
    "Buffalo Trail",
    "Frog Space Program",
    "Fortune Five 20 Lines",
    "Fruitfellas: Fortune Wheel",
    "Wolf of Wild Street",
    "Giggly Greedy Story",
    "Conquest Era",
    "Xiaos Treasures",
    "WildStock",
    "Tritons Realm",
    "Fruitfellas Xmas Wheel",
    "Totem de Oro",
    "Fortune Christmas Wild",
    "Capy Park",
    "Wolf of Xmas Street",
    "Sweet Bazaar",
    "Spin 4 Dead",
    "Clint West Wild",
    "Throne of Camelot",
    "Ganesha Legends",
    "Book of Ancients",
    "Slotout",
    "Witch Treasures",
    "Dangerous Monster",
    "Raging Lion"
],
      "fugaso": [
"Inferno Fireballs: RUNNING WINS",
    "Mexican Coins: CASH UP",
    "Jewel Sea Pirate Riches",
    "Tropical Gold",
    "Striking Diamond: RUNNING WINS",
    "Moon Of Ra: Running Wins",
    "Inferno Diamonds 100",
    "Fruits Royale",
    "Egypt Coin Link: Running Wins",
    "Diamond Blitz 100",
    "Fruits Royale 100",
    "Sugar Paradise",
    "Fruits Royale 5",
    "Striking Coin Link: RUNNING WINS",
    "Midas Links: Running Wins",
    "Xmas Royale",
    "Inferno 777 Re-spins",
    "Into The Jungle Bonus Buy",
    "Super Santa Link: RUNNING WINS",
    "Coin Rush: RHINO RUNNING WINS",
    "Power Wildz: Fruit Saga",
    "Hit The Diamond",
    "EGYPT LINKS: RUNNING WINS",
    "Striking Diamond Link: RUNNING WINS",
    "Inferno Devil 100",
    "Pop&Drop",
    "Fortune Coin Link: RUNNING WINS",
    "City Pop: Hawaii RUNNING WINS",
    "9 DRAGON BALLS: CASH UP",
    "Moon Of Egypt: RUNNING WINS",
    "Book Of Plutus",
    "TRINITY GOLD LINK: RUNNING WINS",
    "Power Boost: Money Express",
    "Trump It Coin Link: RUNNING WINS",
    "Rising Riches Link: RUNNING WINS",
    "Deluxe Fruits 100",
    "Vegas Starstruck: RUNNING WINS",
    "Mega Rich Fruits",
    "Sugar Drop",
    "Coin Rush: Elephant Strike - Running Wins",
    "Power Coin: TRINITY SERIES",
    "Devil's Diamond Rush",
    "Cash Busters",
    "Power Boost: Buffalo Express",
    "Xmas Coins: Running Wins",
    "Zeus Power Link: RUNNING WINS",
    "Thor Power Link: RUNNING WINS",
    "Fat Mama's Wheel",
    "Diamond Blitz 40",
    "Stoned Joker 5",
    "Magic Spinners",
    "Thunderbolt Coin Link: RUNNING WINS",
    "Almighty Hot Wins",
    "Clash Of Gods",
    "INFERNO FIREBALLS 2: RUNNING WINS",
    "Hercules Power Wild",
    "Mexican Mania: Hot Bonus",
    "Xmas Royale 100",
    "Book Of Tattoo 2",
    "Sweet Flips Sugar",
    "Lil Santa",
    "Stoned Joker",
    "Arctic Coins: RUNNING WINS",
    "Book Of Anime",
    "Coin Rush: Gorilla Boost RUNNING WINS",
    "Into The Jungle",
    "The Mummy Win Hunters",
    "Santa's Jingle Wheel",
    "Inferno Diamonds",
    "Thunder Wolf Link: RUNNING WINS",
    "Sugar Drop XMAS",
    "Fortune Circus",
    "Lil' Santa Bonus Buy",
    "King Of The Ring",
    "Magnify Man",
    "The Mummy Win Hunters EPICWAYS"
],
      "quickspin": [
"Eastern Emeralds Megaways",
    "Big Bad Wolf Megaways",
    "Sakura Fortune 2",
    "Sakura Fortune",
    "Panther’s Reign",
    "Big Bad Wolf",
    "Dog Town Deal",
    "Book of Duat",
    "High Street Heist",
    "Cash Truck",
    "Warp Wreckers Power Glyph",
    "Raven Rising",
    "Azticons Chaos Clusters",
    "Flip Royale",
    "Brooklyn Bootleggers",
    "Slugger Time",
    "Sticky Bandits Trail of Blood",
    "Big Bad Wolf Christmas Special",
    "Beastwood",
    "Candy Glyph",
    "Feasting Fox",
    "Cash Truck 2",
    "Book Of Yuletide",
    "Brawlers Bar Cash Collect",
    "Sakura Fortune Epic Bloom",
    "Reel Nightmare",
    "Shields of Lambda",
    "Cash Truck Xmas Delivery",
    "Big Bad Wolf: Pigs of Steel",
    "Scatter Monsters",
    "Golden Glyph 3",
    "Wild Harlequin",
    "Sticky Bandits Unchained",
    "Pineapple Crush",
    "Epic Fish Adventure",
    "Crystal Queens Coins",
    "Spinions X-mas Party",
    "Hammer of Vulcan",
    "Catrina's Coins",
    "Artemis vs Medusa",
    "Betty Bonkers",
    "Golden Glyph 2",
    "Dinosaur Rage",
    "Book of Inferno",
    "Reno 7's",
    "Sticky Bandits 3: Most Wanted",
    "Pearl o Plinko – Mermaid Cove",
    "Mine & Melt",
    "Titan Thunder: Wrath of Hades",
    "Adventures Beyond Wonderland Magical Maze",
    "Guardian of Athens",
    "Temple of Paw",
    "Crystal Prince",
    "Spinions Game Day",
    "Primal Spirits",
    "Vampire Senpai",
    "Cabin Crashers",
    "Wild Luchador",
    "Midas Coins",
    "Sevens High Ultra",
    "Loco the Monkey",
    "Crown of Valor",
    "Ghost Glyph",
    "Blue Fortune",
    "Sinbad",
    "Big Bot Crew",
    "Eastern Emeralds",
    "Ivan and the Immortal King",
    "Polar Paws",
    "Cash Truck 3 Turbo",
    "Crystal Queen",
    "Divine Dreams",
    "Goldilocks",
    "Joker Strike",
    "Sticky Bandits",
    "The Grand",
    "Skulls UP!",
    "Ark of Mystery",
    "Hall of the Mountain King",
    "Tales of Dr. Dolittle",
    "Golden Glyph",
    "Prime Zone",
    "Wild Cauldron",
    "Dragon Shrine",
    "Dwarfs Gone Wild",
    "King Colossus",
    "Mayana",
    "Mighty Arthur",
    "Northern Sky",
    "Phoenix Sun",
    "Pied Piper",
    "Pirate's Charm",
    "Wild Chase: Tokyo Go",
    "Rapunzel's Tower",
    "Spinions",
    "Ticket to the stars",
    "Tiger's Glory",
    "Volcano Riches",
    "Wins of Fortune",
    "Nero's Fortune",
    "Diamond Duke",
    "Wild Tome of the Woods",
    "Sticky Bandits: Wild Return",
    "Fairy Gate",
    "Gold Lab",
    "Hot Sync",
    "Illuminous",
    "Leprechaun Hills",
    "Razortooth",
    "Second Strike",
    "Sevens High",
    "The Wild Chase",
    "Treasure Island",
    "Durian Dynamite",
    "Arcane Gems"
],
      "wizard": [
        "Teddy's Tavern",
    "12 Super Hot Diamonds",
    "Dragon's of the North MegaWays",
    "Surtr's Fury",
    "Awww, So Cute!",
    "Cakes of Fortune",
    "Digipays",
    "12 Super Hot Diamonds Extreme!",
    "Incan Treasures",
    "Madame Voodoo",
    "The Funky Boombox",
    "Chicken Burst",
    "Wild Fruit Super Wheel",
    "Captains of the Coast 2",
    "Fortune Tree of Wealth",
    "Ice Ice Hockey",
    "Spirit Of Mustang",
    "Treasure Temple",
    "Amun Ra - King of the Gods",
    "Princess Celina and the Frog",
    "Dreamy Divas",
    "Alice Mega Riches",
    "Scrolls of Aphrodite",
    "Piggi Bank",
    "Treasures of The Count",
    "Lucky Lamp",
    "Fisherman’s Bounty",
    "Sultan's Palace Fortune",
    "Carnival of Calacas",
    "Bier Haus Riches",
    "Wildwood Buffalo",
    "Santa's Fortune",
    "Wild West Ways",
    "Santa Bonanza",
    "Thor's Hammer Strike",
    "Sizzling Mystery",
    "Jingle Wins",
    "La Mafia Heist",
    "Golden Elk",
    "Grand Pepper Party",
    "Gods of Kemet",
    "Mammoth Mayhem",
    "Catchin’ Fortunes",
    "Super Hot Joker",
    "Tiger Emperor",
    "Alice in Vegasland",
    "Wild Wild Pistols",
    "Towers Of Olympus",
    "Boitatá The Fire Guardian",
    "Fisherman’s Bounty Deluxe",
    "Hot Hot 777",
    "Wolf Riches",
    "Bring In The Fish",
    "Flamin'7s",
    "Captains of the Coast",
    "Wild Wild Wynmor",
    "Majestic North",
    "Coin Fever",
    "Stallion Fortunes",
    "Phoenix Kingdom",
    "Book of Enternal Romance",
    "Vampire’s Secret Treasures",
    "King Koko's Quest",
    "Emeralds of Oz",
    "Froots",
    "Alice Riches",
    "The Good, the Bad & The Wild",
    "Book of Enchantments",
    "Cup Glory",
    "Sweet Feast",
    "Goddess Of Fortunes",
    "Jade King",
    "Dragons of the North Deluxe",
    "Rumble Rhino MEGAWAYS",
    "Tiki Magic",
    "Power Strike Super Spin",
    "Aesir Treasures",
    "Bier Party",
    "Unchain the Dragons",
    "Lucky Keno",
    "Wild Candy",
    "King of the Trident Deluxe",
    "The Secret Order",
    "Gold's Guardian",
    "Mystery Fox Christmas Party",
    "Phoenix Gold",
    "Book of Itza",
    "Jackpot Fortunes",
    "Hot Wild 7s",
    "Grand Loot",
    "Epic Riches",
    "The Thunderer",
    "The Prancing Pony",
    "Force of the Gods",
    "Wild Fortunes",
    "Faith",
    "Magic Baccarat",
    "Fruity Friends",
    "Fortune Dragons",
    "Rio Fever",
    "Cops And Robbers",
    "Aloha Fortune",
    "Titans Riches",
    "Las Cucas Locas",
    "Torro's Gold",
    "The Alchemist",
    "Spin N' Hit",
    "Bubble Hits",
    "Joker Joker",
    "Amazing Riches",
    "Fruit Basket",
    "Luxor Scratch",
    "Dragon Scrolls",
    "Fire Vs. Ice",
    "XO Manowar",
    "Chitty Bang",
    "Goddess Of The Moon",
    "Tokyo Nights",
    "Jonny Ventura And The Eye Of Ra",
    "Santa's Workshop",
    "BloodShot Rising Spirit",
    "BloodShot",
    "Mystery Fox",
    "Barn Ville",
    "Mega Love",
    "Rio Bingo",
    "Pot O'Gold",
    "Ocean Fortune",
    "Zodiac Fortune",
    "Cash Cuisine",
    "Zombies Gone Wild",
    "Royal Charm",
    "European Roulette Min: 0.10c",
    "European Roulette High Stakes",
    "Pets 94",
    "Bai She Zhuan",
    "World Cup Keno",
    "Dragons of the North",
    "Goldorado",
    "Wild Cherry",
    "Luxor",
    "Fur Balls",
    "Parrot's Gold",
    "Viking Glory",
    "Sweetie Land",
    "Fruit Abduction",
    "Magical Forest",
    "Fish and Chips",
    "I Love Christmas",
    "Lucky Vegas",
    "Jack In The Box",
    "Xi You Ji",
    "King of the Trident",
    "Mystic Manor",
    "Jack’s Treasure",
    "Gems and Riches"
],
      "voltent" [
 "25 Coins",
  "12 Bells",
  "16 Coins",
  "20 Coins",
  "36 Coins",
  "9 Coins",
  "Hot Slot: 777 Coins",
  "Mighty Symbols: Crowns",
  "9 Coins Grand Diamond Edition",
  "Power of Gods: Medusa",
  "Book of Faith",
  "Mighty Wild: Panther Halloween Edition",
  "Hot Slot: 777 Coins Extremely Light",
  "Football Mania Deluxe",
  "Mighty Wild: Panther",
  "Mighty Fish Blue Marlin",
  "9 Bells",
  "9 Lions",
  "Hot Slot: Magic Pearls",
  "12 Coins Grand Gold Edition",
  "24 Coins",
  "9 Coins Extremely Light",
  "Butterfly Lovers",
  "30 Coins",
  "Jacks Ride",
  "Mighty Symbols: Diamonds",
  "Lucky Fortune",
  "Hot Slot: 777 Cash Out Extremely Light",
  "Mighty Wild: Panther Grand Diamond Edition Love the Jackpot",
  "9 Coins Grand Diamond Xmas",
  "Hot Slot: Great Book Of Magic",
  "Power of Gods: Valhalla",
  "12 Coins",
  "16 Coins Grand Gold Edition",
  "Mighty Wild: Panther Grand Gold Edition",
  "20 Coins Halloween Jackpots",
  "12 Coins Grand Diamond Edition",
  "Hot Slot: 777 Stars",
  "Moon Of Fortune",
  "Mighty Wild: Jaguar",
  "16 Coins Xmas",
  "Mighty Wild: Panther Xmas",
  "Power of Gods: Hades Love the Jackpot",
  "36 Coins Halloween Jackpots",
  "9 Coins Love the Jackpot",
  "Hot Slot: 777 Cash Out Xmas",
  "16 Coins Grand Platinum Edition",
  "Mighty Wild: Panther Grand Platinum Edition Santas Jackpots",
  "Hot Slot: 777 Crown Extremely Light",
  "Burning Sun Easter",
  "20 Coins Grand Gold Edition",
  "9 Bells Love the Jackpot",
  "Black Horse Cash Out",
  "Mighty Wild: Panther Grand Diamond Edition",
  "Mighty Symbols Jokers Santas Jackpots",
  "Hot Slot: 777 Cash Out Grand Gold Edition",
  "Los Muertos 2",
  "Hot Slot: 777 Rubies Extremely Light",
  "16 Coins Love the Jackpot",
  "16 Coins Halloween Edition",
  "Mighty Wild: Panther Grand Platinum Edition",
  "Magic Spins Love the Jackpot",
  "Sizzling Eggs Halloween Edition",
  "25 Coins Santas Jackpots",
  "25 Coins Grand Gold Edition",
  "9 Coins Grand Diamond Love the Jackpot",
  "Prosperity Reels",
  "Burning Sun Extremely Light",
  "Hot Slot: 777 Cash Out Halloween Edition",
  "9 Lions Hold the Jackpot Halloween Jackpots",
  "15 Coins Grand Gold Edition",
  "Mighty Wild: Panther Grand Diamond Edition Halloween Jackpots",
  "36 Coins Love the Jackpot",
  "Mighty Wild: Jaguar Love the Jackpot",
  "15 Coins: Grand Platinum Edition",
  "9 Lions Hold the Jackpot",
  "Hot Slot: 777 Cash Out Grand Platinum Edition",
  "Hot Slot: 777 Cash Out Grand Diamond Edition",
  "Night Club 81",
  "Hot Slot: 777 Stars Extremely Light",
  "16 Coins Grand Gold Edition Santas Jackpots",
  "Burning Sun",
  "Mighty Wild: Panther Easter",
  "25 Coins Easter",
  "Mighty Symbols: Sevens",
  "Power of Gods: Valhalla Extremely Light",
  "20 Coins Score The Jackpot",
  "Hot Slot: 777 Cash Out Easter",
  "30 Coins Score the Jackpot",
  "36 Coins Score the Jackpot",
  "One Coin",
  "9 Coins Grand Platinum Edition Score the Jackpot",
  "20 Coins Easter",
  "12 Coins: Grand Platinum Edition",
  "Mighty Symbols: Jokers",
  "Jelly Reels Xmas Edition",
  "9 Coins Xmas",
  "Dwarfs Fortune",
  "9 Burning Stars",
  "9 Coins Grand Gold Edition",
  "9 Coins Grand Platinum Edition",
  "Jack on Hold",
  "Jelly Reels",
  "9 Coins 1000x Edition",
  "Dwarfs Fortune Easter",
  "Hot Slot: 777 Cash Out",
  "Power of Sun: Svarog",
  "Sizzling Kingdom: Bison",
  "Choco Reels Easter",
  "Sizzling Eggs Extremely Light",
  "Hot Slot: 777 Crown",
  "Magic Spins Xmas Edition",
  "Hot Slot: Magic Bombs",
  "Hot Slot: Mystery Jackpot Joker",
  "9 Coins Halloween",
  "Larry the Leprechaun",
  "Magic Spins",
  "Mystery Kingdom: Mystery Bells",
  "Power of Gods: Medusa Easter",
  "Burning Stars 3 Xmas",
  "Larry the Leprechaun Easter",
  "Sizzling Eggs",
  "Power of Gods: Medusa Extremely Light",
  "9 Burning Dragons",
  "Magic Eggs",
  "Burning Stars 3",
  "15 Coins",
  "Cube Mania",
  "Fortune Reels",
  "Neon City",
  "9 Lions Xmas Edition",
  "Midnight in Tokyo",
  "Cube Mania Deluxe",
  "Sun Of Fortune Xmas Edition",
  "Prosperity Pearls",
  "Power of Gods: Egypt",
  "Sizzling Moon",
  "Sizzling Bells",
  "Hot Slot: 777 Rubies",
  "Welcome To Hell 81",
  "Magic Of The Ring",
  "Reel Hero",
  "Reel Joke",
  "Lucky 9",
  "Unicorn Reels",
  "Sun of Fortune",
  "Power of Gods: Hades",
  "Fruit Mania",
  "Black Horse Deluxe",
  "Dragons Lucky 8",
  "Telly Reel",
  "Gem Splitter",
  "Choco Reels",
  "Wild Jack 81",
  "Hot Party Deluxe",
  "Relic Hunters and the Book of Faith",
  "Magic Stars 9",
  "9 Tigers",
  "Clover Lady",
  "Joker Poker",
  "Turbo Poker",
  "Three Cards",
  "Magic Poker",
  "Caribbean Beach Poker",
  "Extra Bingo",
  "Bell Wizard",
  "Casino Roulette",
  "Great Book Of Magic Deluxe",
  "Black Hawk Deluxe",
  "Lucky Reels",
  "Infinity Hero",
  "Black Hawk",
  "Vegas Reels II",
  "Fire Bird",
  "Magic Hot 4 Deluxe",
  "Lucky Fish",
  "Burning Stars",
  "Back to the 70s",
  "Gold Roulette",
  "Spectrum",
  "Wild Guns",
  "BARs & 7s",
  "Fruit Mania Deluxe",
  "Corrida Romance Deluxe",
  "Fruit Fiesta",
  "Sonic Reels",
  "Highschool Manga",
  "Sizzling 777 Deluxe",
  "Fruits Go Bananas",
  "Fenix Play 27",
  "Magic Of The Ring Deluxe",
  "Highway to Hell Deluxe",
  "Lost Treasure",
  "Slot Jam",
  "Valhalla",
  "Los Muertos",
  "Golden Sphinx",
  "Triple Star",
  "KickOff",
  "Crazy Cars",
  "Hot Party",
  "Demon Jack 27",
  "Power of Gods: The Pantheon",
  "Draculas Castle",
  "Dino Reels 81",
  "Wild Jack",
  "Magic Fruits 4",
  "Jackpot Builders",
  "Turbo Play",
  "Vegas Hot",
  "Beach Party",
  "Mayan Ritual",
  "Jumping Fruits",
  "Mystery Jack",
  "Magic Fruits 81",
  "Haunted Hospital",
  "Criss Cross 81",
  "In The Forest",
  "Highway to Hell",
  "Double Tigers",
  "Corrida Romance",
  "Fenix Play",
  "Wild Girls",
  "Joker Explosion",
  "Super Hot",
  "Magic Stars",
  "Hot 777",
  "Miami Beach",
  "Juicy Reels",
  "American Poker V",
  "Good Luck 40",
  "Magic Target",
  "Win & Replay",
  "American Poker Gold",
  "Magic Hot 4",
  "Beach Party Hot",
  "Vegas Hot 81",
  "Magic Fruits 27",
  "Magic Fruits Deluxe"
],
        "egt": [
        "40 Super Hot Bell Link",
        "40 Super Hot Bell Link",
        "Flaming Hot Extreme Bell Link",
        "40 Shining Crown Bell Link",
        "40 Burning Hot 6 Reels",
        "Shining Crown",
        "100 Burning Hot",
        "20 Super Hot Bell Link",
        "Flaming Hot Bell Link",
        "Burning Hot Bell Link",
        "40 Burning Clover 6 Reels",
        "40 Burning Hot",
        "40 Super Fruits Bell Link",
        "Flaming Hot Extreme",
        "40 Shining Crown",
        "Shining Crown Bell Link",
        "40 Lucky King Bell Link",
        "Vampire Night Bell Link",
        "40 Lucky King Extreme Bell Link"
    ]
    }
  }
}
